MANIFEST.in
README.rst
setup.py
twisted/plugins/udtplugin.py
twisted/plugins/udtplugin.pyc
udt4twisted/__init__.py
udt4twisted/udt.py
udt4twisted/udtepollreactor.py
udt4twisted.egg-info/PKG-INFO
udt4twisted.egg-info/SOURCES.txt
udt4twisted.egg-info/dependency_links.txt
udt4twisted.egg-info/requires.txt
udt4twisted.egg-info/top_level.txt