Metadata-Version: 1.1
Name: udt4twisted
Version: 0.2.6
Summary: An UDT4 integration package for twisted.
Home-page: UNKNOWN
Author: Martin N. Gergov
Author-email: martingergov1@gmail.com
License: GPLv3
Download-URL: https://bitbucket.org/marto1/udt4twisted/
Keywords: udt4twisted,pyudt,udt4,twisted
Platform: UNKNOWN
Classifier: License :: OSI Approved :: GNU General Public License v3 (GPLv3)
Classifier: Topic :: Software Development :: Libraries
Classifier: Programming Language :: Python :: 2.7
